CHANGES
LICENSE
MANIFEST.in
README.rst
setup.py
django_screamshot.egg-info/PKG-INFO
django_screamshot.egg-info/SOURCES.txt
django_screamshot.egg-info/dependency_links.txt
django_screamshot.egg-info/not-zip-safe
django_screamshot.egg-info/requires.txt
django_screamshot.egg-info/top_level.txt
screamshot/__init__.py
screamshot/admin.py
screamshot/decorators.py
screamshot/managers.py
screamshot/models.py
screamshot/tests.py
screamshot/urls.py
screamshot/utils.py
screamshot/views.py
screamshot/scripts/capture-phantomjs.js
screamshot/scripts/capture.js
screamshot/templatetags/__init__.py
screamshot/templatetags/screamshot.py