Metadata-Version: 1.1
Name: django-screamshot
Version: 0.8.2
Summary: Web pages capture using Django & CasperJS
Home-page: https://github.com/makinacorpus/django-screamshot
Author: Mathieu Leplatre
Author-email: mathieu.leplatre@makina-corpus.com
License: LPGL, see LICENSE file.
Platform: UNKNOWN
Classifier: Natural Language :: English
Classifier: Operating System :: OS Independent
Classifier: Environment :: Web Environment
Classifier: Framework :: Django
Classifier: Programming Language :: Python :: 2.7
